ephemetoot/__init__.py
ephemetoot/console.py
ephemetoot/ephemetoot.py
ephemetoot/plist.py
ephemetoot-3.2.1.dist-info/LICENSE
ephemetoot-3.2.1.dist-info/METADATA
ephemetoot-3.2.1.dist-info/WHEEL
ephemetoot-3.2.1.dist-info/entry_points.txt
ephemetoot-3.2.1.dist-info/top_level.txt
ephemetoot-3.2.1.dist-info/RECORD
