Metadata-Version: 2.1
Name: ephemetoot
Version: 3.2.1
Summary: A command line tool to delete your old toots
Author-email: Hugh Rundle <ephemetoot@hugh.run>
License: GPL-3.0-or-later
Project-URL: homepage, https://ephemetoot.hugh.run
Project-URL: repository, https://github.com/hughrun/ephemetoot
Keywords: mastodon,api,microblogging
Classifier: Environment :: Console
Classifier: Operating System :: OS Independent
Classifier: Topic :: Communications
Requires-Python: >=3.8
License-File: LICENSE
Requires-Dist: requests >=2.31.0
Requires-Dist: mastodon.py >=1.8.1
Requires-Dist: pyyaml >=6.0.1
Provides-Extra: dev
Requires-Dist: pytest >=6 ; extra == 'dev'
